bfinn/__init__.py
bfinn/bfinn.py
bfinn/data/BFINN-111.txt
bfinn/data/BFINN-96.txt
bfinn/data/BFINN-da-32.txt
bfinn/data/BFINN-emoticon-8.txt
bfinn/data/BFINN-en-165.txt
bfinn/data/BFINN-fr-165.txt
bfinn/data/BFINN-sv-165.txt
bfinn-0.2.dist-info/LICENSE
bfinn-0.2.dist-info/METADATA
bfinn-0.2.dist-info/WHEEL
bfinn-0.2.dist-info/top_level.txt
bfinn-0.2.dist-info/RECORD
