Metadata-Version: 2.1
Name: bfinn
Version: 0.2
Summary: AFINN sentiment analysis with different english wordlist
Home-page: https://github.com/ngeorgescu/bfinn
Author: Nicholas Georgescu
Author-email: ngeorgescu@gmail.com
License: Apache License 2.0
Keywords: sentiment analysis
Platform: UNKNOWN
